pyccoma/__init__.py
pyccoma/__main__.py
pyccoma/dd.py
pyccoma/exceptions.py
pyccoma/helpers.py
pyccoma/logger.py
pyccoma/pyccoma.py
pyccoma/utils.py
pyccoma/fr/__init__.py
pyccoma/fr/pyccoma.py
pyccoma/fr/urls.py
pyccoma/jp/__init__.py
pyccoma/jp/pyccoma.py
pyccoma/jp/urls.py
pyccoma-0.7.2.dist-info/LICENSE
pyccoma-0.7.2.dist-info/METADATA
pyccoma-0.7.2.dist-info/WHEEL
pyccoma-0.7.2.dist-info/entry_points.txt
pyccoma-0.7.2.dist-info/top_level.txt
pyccoma-0.7.2.dist-info/RECORD
