Metadata-Version: 2.1
Name: pyccoma
Version: 0.7.2
Summary: Scrape and download from Piccoma Japan and France.
Home-page: https://github.com/catsital/pyccoma
Author: catsital
Author-email: catshital@gmail.com
Project-URL: Bug Tracker, https://github.com/catsital/pyccoma/issues
Classifier: Programming Language :: Python :: 3
Classifier: License :: OSI Approved :: Apache Software License
Classifier: Operating System :: OS Independent
Requires-Python: >=3.8
License-File: LICENSE
Requires-Dist: lxml >=4.7.1
Requires-Dist: requests ==2.26.0
Requires-Dist: image-scramble ==2.0.1
